bedrock_inference/__init__.py
bedrock_inference/bedrock.py
bedrock_inference-0.0.13.dist-info/LICENSE
bedrock_inference-0.0.13.dist-info/METADATA
bedrock_inference-0.0.13.dist-info/WHEEL
bedrock_inference-0.0.13.dist-info/top_level.txt
bedrock_inference-0.0.13.dist-info/RECORD
