Metadata-Version: 2.1
Name: bedrock_inference
Version: 0.0.13
Summary: Login into your AWS and call Bedrock models in Python
Author-email: Tommaso Mario Buonocore <tommaso.buonocore@unipv.it>
License: MIT License
Project-URL: Homepage, https://github.com/detsutut/bedrock_inference
Project-URL: Issues, https://github.com/detsutut/bedrock_inference/issues
Keywords: aws,bedrock,llm,inference,generative_ai
Classifier: Programming Language :: Python :: 3
Classifier: License :: OSI Approved :: MIT License
Classifier: Operating System :: OS Independent
Requires-Python: >=3.8
License-File: LICENSE
Requires-Dist: beautifulsoup4 >=4.12
Requires-Dist: boto3 >=1.35
Requires-Dist: botocore >=1.35
Requires-Dist: pandas >=2.2
